holtwinters/__init__.py
holtwinters/ad_hw.py
holtwinters-1.0.dist-info/LICENSE
holtwinters-1.0.dist-info/METADATA
holtwinters-1.0.dist-info/WHEEL
holtwinters-1.0.dist-info/top_level.txt
holtwinters-1.0.dist-info/RECORD
