Metadata-Version: 2.1
Name: holtwinters
Version: 1.0
Summary: Holt winters for anomaly detection
Home-page: https://pip.pypa.io/
Author: arunsechergy
Author-email: arun.rvbe@gmail.com
License: MIT
Platform: UNKNOWN
